{
    "AltUp": "None",
    "AltDown": "None",
    "AltLeft": "None",
    "AltRight": "None",
    "AltShiftLeft": "None",
    "AltShiftRight": "None",
    "CtrlUp": "ParagraphPrevious",
    "CtrlDown": "ParagraphNext",
    "CtrlShiftUp": "None",
    "CtrlShiftDown": "None",
    "Alt-{": "None",
    "Alt-}": "None",
    "Ctrl-h": "None",
    "Ctrl-t": "None",
    "Ctrl-w": "Quit",
    "Alt-CtrlH": "None",
    "Ctrl-o": "None",
    "Ctrl-n": "None",
    "Ctrl-p": "None",
    "Ctrl-d": "FindPrevious",
    "Ctrl-g": "FindNext",
    "CtrlPageUp": "None",
    "CtrlPageDown": "None",
    "Alt-g": "None",
    "Ctrl-r": "None",
    "Ctrl-b": "None",
    "Ctrl-q": "None",
    "Alt-f": "None",
    "Alt-b": "None",
    "Alt-a": "None",
    "Alt-e": "None",
    "F2": "None",
    "F3": "None",
    "F4": "None",
    "F7": "None",
    "F10": "None",
    "CtrlEnd": "CursorEnd",
}
